{
  "alacritty-catppuccin": {
    "cargoLock": null,
    "date": "2024-10-28",
    "extract": null,
    "name": "alacritty-catppuccin",
    "passthru": null,
    "pinned": false,
    "src": {
      "deepClone": false,
      "fetchSubmodules": false,
      "leaveDotGit": false,
      "name": null,
      "owner": "catppuccin",
      "repo": "alacritty",
      "rev": "f6cb5a5c2b404cdaceaff193b9c52317f62c62f7",
      "sha256": "sha256-H8bouVCS46h0DgQ+oYY8JitahQDj0V9p2cOoD4cQX+Q=",
      "sparseCheckout": [],
      "type": "github"
    },
    "version": "f6cb5a5c2b404cdaceaff193b9c52317f62c62f7"
  },
  "easytier-latest": {
    "cargoLock": null,
    "date": null,
    "extract": null,
    "name": "easytier-latest",
    "passthru": null,
    "pinned": false,
    "src": {
      "deepClone": false,
      "fetchSubmodules": false,
      "leaveDotGit": false,
      "name": null,
      "owner": "EasyTier",
      "repo": "EasyTier",
      "rev": "v2.6.4",
      "sha256": "sha256-lwqpOVKFm85AiBb7NWLAkjSrWSe5pzF0AuEmmDo+v0k=",
      "sparseCheckout": [],
      "type": "github"
    },
    "version": "v2.6.4"
  },
  "fakehttp": {
    "cargoLock": null,
    "date": null,
    "extract": null,
    "name": "fakehttp",
    "passthru": null,
    "pinned": false,
    "src": {
      "name": null,
      "sha256": "sha256-DNvjQndYez6f+BF+YTDV241xa7nFFDRAiEpSftHVv8k=",
      "type": "url",
      "url": "https://github.com/MikeWang000000/FakeHTTP/releases/download/0.9.18/fakehttp-linux-x86_64.tar.gz"
    },
    "version": "0.9.18"
  },
  "haier": {
    "cargoLock": null,
    "date": "2026-05-28",
    "extract": null,
    "name": "haier",
    "passthru": null,
    "pinned": false,
    "src": {
      "deepClone": false,
      "fetchSubmodules": false,
      "leaveDotGit": false,
      "name": null,
      "owner": "banto6",
      "repo": "haier",
      "rev": "b5cd1f03c6f99e0f1824a5600456e5c53b57ed4e",
      "sha256": "sha256-9eRSEL1pVbC4mquL0D4lwFvmethMidK1S+W+e3rI5s8=",
      "sparseCheckout": [],
      "type": "github"
    },
    "version": "b5cd1f03c6f99e0f1824a5600456e5c53b57ed4e"
  },
  "kitty-catppuccin": {
    "cargoLock": null,
    "date": "2026-01-16",
    "extract": null,
    "name": "kitty-catppuccin",
    "passthru": null,
    "pinned": false,
    "src": {
      "deepClone": false,
      "fetchSubmodules": false,
      "leaveDotGit": false,
      "name": null,
      "owner": "catppuccin",
      "repo": "kitty",
      "rev": "43098316202b84d6a71f71aaf8360f102f4d3f1a",
      "sha256": "sha256-akRkdq8l2opGIg3HZd+Y4eky6WaHgKFQ5+iJMC1bhnQ=",
      "sparseCheckout": [],
      "type": "github"
    },
    "version": "43098316202b84d6a71f71aaf8360f102f4d3f1a"
  },
  "kxy-script": {
    "cargoLock": null,
    "date": null,
    "extract": null,
    "name": "kxy-script",
    "passthru": null,
    "pinned": false,
    "src": {
      "name": null,
      "sha256": "sha256-jOlBBLIjT0lYKPkgxIKaUGwuEeR/O4rupG1SpZ4n8pw=",
      "type": "url",
      "url": "https://cdn.kxy.ovh/kxy.sh"
    },
    "version": "V1.2"
  },
  "realm-latest": {
    "cargoLock": null,
    "date": null,
    "extract": null,
    "name": "realm-latest",
    "passthru": null,
    "pinned": false,
    "src": {
      "deepClone": false,
      "fetchSubmodules": false,
      "leaveDotGit": false,
      "name": null,
      "owner": "zhboner",
      "repo": "realm",
      "rev": "v2.9.4",
      "sha256": "sha256-gnsFqWhJOMKUaSWfRmHBksw3uWFP0smRhEbPLriEmlk=",
      "sparseCheckout": [],
      "type": "github"
    },
    "version": "v2.9.4"
  },
  "rime-wanxiang-base": {
    "cargoLock": null,
    "date": null,
    "extract": null,
    "name": "rime-wanxiang-base",
    "passthru": null,
    "pinned": false,
    "src": {
      "name": null,
      "sha256": "sha256-DvYKwWgKDQUYRDPyuYJw6mhyvsmojlB9EdEUYzTp30A=",
      "type": "url",
      "url": "https://github.com/amzxyz/rime_wanxiang/releases/download/v15.12.3/rime-wanxiang-base.zip"
    },
    "version": "v15.12.3"
  },
  "rime-wanxiang-gram": {
    "cargoLock": null,
    "date": null,
    "extract": null,
    "name": "rime-wanxiang-gram",
    "passthru": null,
    "pinned": false,
    "src": {
      "name": null,
      "sha256": "sha256-Pr3wgPM9TzYY8medb540opC9dZBvQrnXU/Yw5RAeVAc=",
      "type": "url",
      "url": "https://github.com/amzxyz/RIME-LMDG/releases/download/LTS/wanxiang-lts-zh-hans.gram"
    },
    "version": "LTS"
  },
  "save-restricted-content-bot": {
    "cargoLock": null,
    "date": "2025-11-19",
    "extract": null,
    "name": "save-restricted-content-bot",
    "passthru": null,
    "pinned": false,
    "src": {
      "deepClone": false,
      "fetchSubmodules": false,
      "leaveDotGit": false,
      "name": null,
      "owner": "VJBots",
      "repo": "VJ-Save-Restricted-Content",
      "rev": "93129e163377f0ce292471c6f202f8eaf40106d1",
      "sha256": "sha256-Tfb3RLkH+CLSlUQDxzzf91ZK/zNFuMLiz3RjA5yyvUI=",
      "sparseCheckout": [],
      "type": "github"
    },
    "version": "93129e163377f0ce292471c6f202f8eaf40106d1"
  },
  "send2kindlebot": {
    "cargoLock": null,
    "date": "2026-05-28",
    "extract": null,
    "name": "send2kindlebot",
    "passthru": null,
    "pinned": false,
    "src": {
      "deepClone": false,
      "fetchSubmodules": false,
      "leaveDotGit": false,
      "name": null,
      "owner": "gabrielrf",
      "repo": "send2kindlebot",
      "rev": "6ad28eb2ba47eaf9c47a0c531d8a8218e9b1fd49",
      "sha256": "sha256-uCYV87kGmUL/e1WhkiZDVDaZWgk9992z0iQOrgqbejc=",
      "sparseCheckout": [],
      "type": "github"
    },
    "version": "6ad28eb2ba47eaf9c47a0c531d8a8218e9b1fd49"
  },
  "wallpaper": {
    "cargoLock": null,
    "date": null,
    "extract": null,
    "name": "wallpaper",
    "passthru": null,
    "pinned": false,
    "src": {
      "name": "wallpaper.jpg",
      "sha256": "sha256-wkiXDN6vPFtx88krcQ4szK6dJNjtrDxrsNa3ZvHlfMQ=",
      "type": "url",
      "url": "https://files.yande.re/image/3fc51f6a2fb10c96b73dd0fce6ddb9c8/yande.re%201048717%20dress%20garter%20lolita_fashion%20ruo_gan_zhua.jpg"
    },
    "version": "latest"
  }
}
